nwtk/__init__.py
nwtk/_activation.py
nwtk/_core.py
nwtk/_edgeinfo.py
nwtk/_embedding.py
nwtk/_manipulate.py
nwtk/_nodeinfo.py
nwtk/_rbf_basis.py
nwtk/_version.py
nwtk/attention.py
nwtk/config.py
nwtk/convposenc.py
nwtk/downsample.py
nwtk/drop.py
nwtk/graph.py
nwtk/helpers.py
nwtk/lortzen.py
nwtk/mlp.py
nwtk/norm.py
nwtk/utils.py
nwtk-0.1.2.dist-info/METADATA
nwtk-0.1.2.dist-info/WHEEL
nwtk-0.1.2.dist-info/licenses/LICENSE
nwtk-0.1.2.dist-info/RECORD
