Metadata-Version: 2.4
Name: nwtk
Version: 0.1.2
Summary: Your project description here
Project-URL: Homepage, https://github.com/xia0WT/nwtk
Project-URL: Repository, https://github.com/xia0WT/nwtk
Author-email: zeb <zebscg@gmail.com>
License: Copyright 2025 Zhang Eb
License-File: LICENSE
Keywords: example,nwtk,python
Classifier: License :: OSI Approved :: MIT License
Classifier: Operating System :: OS Independent
Classifier: Programming Language :: Python :: 3
Requires-Python: >=3.10
Requires-Dist: numpy>=1.25
Requires-Dist: torch<2.7.0,>=2.3.1
Provides-Extra: full
Requires-Dist: dgl>=2.1.0; extra == 'full'
Provides-Extra: test
Requires-Dist: pytest>=6.0; extra == 'test'
